queryparams/__init__.py
queryparams_liberdade-0.0.1.dist-info/LICENSE
queryparams_liberdade-0.0.1.dist-info/METADATA
queryparams_liberdade-0.0.1.dist-info/WHEEL
queryparams_liberdade-0.0.1.dist-info/top_level.txt
queryparams_liberdade-0.0.1.dist-info/RECORD
