Metadata-Version: 2.1
Name: queryparams-liberdade
Version: 0.0.1
Summary: Objects as query parameters
Home-page: https://github.com/liberdade-organizacao/queryparams
Author: Cristiano Silva Jr
Author-email: crisjr@pm.me
License: UNKNOWN
Platform: UNKNOWN
Classifier: Programming Language :: Python :: 3
Classifier: License :: OSI Approved :: MIT License
Classifier: Operating System :: OS Independent
Requires-Python: >=3.5
